nlweb_models/__init__.py
nlweb_models/embedding/__init__.py
nlweb_models/embedding/azure_oai_embedding.py
nlweb_models/embedding/elasticsearch_embedding.py
nlweb_models/embedding/gemini_embedding.py
nlweb_models/embedding/ollama_embedding.py
nlweb_models/embedding/openai_embedding.py
nlweb_models/embedding/snowflake_embedding.py
nlweb_models/llm/__init__.py
nlweb_models/llm/anthropic.py
nlweb_models/llm/azure_deepseek.py
nlweb_models/llm/azure_llama.py
nlweb_models/llm/azure_oai.py
nlweb_models/llm/gemini.py
nlweb_models/llm/huggingface.py
nlweb_models/llm/inception.py
nlweb_models/llm/llm_provider.py
nlweb_models/llm/ollama.py
nlweb_models/llm/openai.py
nlweb_models/llm/pi_labs.py
nlweb_models/llm/snowflake.py
nlweb_models-0.5.6.dist-info/METADATA
nlweb_models-0.5.6.dist-info/WHEEL
nlweb_models-0.5.6.dist-info/top_level.txt
nlweb_models-0.5.6.dist-info/RECORD
