Metadata-Version: 2.4
Name: nlweb-models
Version: 0.5.6
Summary: Model bundle for NLWeb - includes embedding and LLM interfaces for multiple providers
Author: Microsoft Corporation
License: MIT
Project-URL: Homepage, https://github.com/microsoft/NLWeb_Core
Project-URL: Repository, https://github.com/microsoft/NLWeb_Core
Project-URL: Issues, https://github.com/microsoft/NLWeb_Core/issues
Classifier: Development Status :: 4 - Beta
Classifier: Intended Audience :: Developers
Classifier: License :: OSI Approved :: MIT License
Classifier: Programming Language :: Python :: 3
Classifier: Programming Language :: Python :: 3.9
Classifier: Programming Language :: Python :: 3.10
Classifier: Programming Language :: Python :: 3.11
Classifier: Programming Language :: Python :: 3.12
Requires-Python: >=3.9
Requires-Dist: nlweb-core>=0.5.5
Requires-Dist: openai>=1.12.0
Requires-Dist: anthropic>=0.18.1
Requires-Dist: google-cloud-aiplatform>=1.38.0
Requires-Dist: azure-identity>=1.12.0
Requires-Dist: huggingface_hub>=0.31.0
Requires-Dist: httpx>=0.28.1
Requires-Dist: aiohttp>=3.8.0
Requires-Dist: elasticsearch[async]<9,>=8
Provides-Extra: dev
Requires-Dist: pytest>=7.0; extra == "dev"
Requires-Dist: pytest-asyncio>=0.21.0; extra == "dev"
